fyodoros/__init__.py
fyodoros/__main__.py
fyodoros/cli.py
fyodoros/os_init.py
fyodoros/bin/__init__.py
fyodoros/bin/agentctl.py
fyodoros/bin/browser.py
fyodoros/bin/calc.py
fyodoros/bin/echo.py
fyodoros/bin/explorer.py
fyodoros/bin/system.py
fyodoros/bin/user.py
fyodoros/kernel/__init__.py
fyodoros/kernel/agent.py
fyodoros/kernel/boot.py
fyodoros/kernel/config.py
fyodoros/kernel/confirmation.py
fyodoros/kernel/device.py
fyodoros/kernel/dom.py
fyodoros/kernel/filesystem.py
fyodoros/kernel/io.py
fyodoros/kernel/kernel.py
fyodoros/kernel/llm.py
fyodoros/kernel/memory.py
fyodoros/kernel/network.py
fyodoros/kernel/plugin_loader.py
fyodoros/kernel/process.py
fyodoros/kernel/resource_monitor.py
fyodoros/kernel/rootfs.py
fyodoros/kernel/sandbox.py
fyodoros/kernel/scheduler.py
fyodoros/kernel/syscall.py
fyodoros/kernel/tty.py
fyodoros/kernel/users.py
fyodoros/kernel/cloud/__init__.py
fyodoros/kernel/cloud/docker_interface.py
fyodoros/kernel/cloud/k8s_interface.py
fyodoros/kernel/senses/listener.py
fyodoros/kernel/senses/motor.py
fyodoros/kernel/senses/ui_driver.py
fyodoros/kernel/shell/__init__.py
fyodoros/kernel/shell/launcher.py
fyodoros/kernel/shell/registrar.py
fyodoros/kernel/shell/supervisor.py
fyodoros/kernel/shell/window_manager.py
fyodoros/kernel/tests/test_io.py
fyodoros/plugins/__init__.py
fyodoros/plugins/registry.py
fyodoros/plugins/github/__init__.py
fyodoros/plugins/slack_notifier/__init__.py
fyodoros/plugins/team_collaboration/__init__.py
fyodoros/plugins/usage_dashboard/__init__.py
fyodoros/server/__init__.py
fyodoros/server/main.py
fyodoros/servicemanager/journal_daemon.py
fyodoros/servicemanager/servicemanager.py
fyodoros/servicemanager/types.py
fyodoros/shell/shell.py
fyodoros/utils/__init__.py
fyodoros/utils/error_recovery.py
fyodoros/utils/logging.py
fyodoros/utils/security.py
fyodoros-0.9.0.dist-info/licenses/LICENSE
fyodoros-0.9.0.dist-info/METADATA
fyodoros-0.9.0.dist-info/WHEEL
fyodoros-0.9.0.dist-info/entry_points.txt
fyodoros-0.9.0.dist-info/top_level.txt
fyodoros-0.9.0.dist-info/RECORD
