Metadata-Version: 2.4
Name: fyodoros
Version: 0.9.0
Summary: FyodorOS: A Compiled AI Microkernel with Native Desktop Interface
Author-email: Kiy-K <khoitruong071510@gmail.com>
Classifier: Programming Language :: Python :: 3
Classifier: License :: OSI Approved :: MIT License
Classifier: Operating System :: OS Independent
Requires-Python: >=3.8
License-File: LICENSE
Requires-Dist: openai
Requires-Dist: google-generativeai
Requires-Dist: anthropic
Requires-Dist: gradio
Requires-Dist: ddgs
Requires-Dist: playwright==1.41.2
Requires-Dist: rich
Requires-Dist: typer
Requires-Dist: requests
Requires-Dist: psutil
Requires-Dist: cryptography
Requires-Dist: argon2-cffi
Requires-Dist: docker>=6.0.0
Requires-Dist: kubernetes>=28.0.0
Requires-Dist: chromadb>=0.4.0
Requires-Dist: pytest
Requires-Dist: pytest-cov
Requires-Dist: pytest-mock
Requires-Dist: nuitka
Requires-Dist: ordered-set
Requires-Dist: fastapi>=0.100.0
Requires-Dist: uvicorn[standard]>=0.20.0
Requires-Dist: websockets>=11.0
Dynamic: license-file
